[
  {
    "dataset_id": "5fbb31eb7716a582080083ba",
    "customer_id": "5fbababa93c0cf8b83f4d7cf",
    "dataset_title": "Dataset about members",
    "people": [
      {
        "person_id": "5fbb31ebc576c5b04e7e588a",
        "person_name_first": "House",
        "person_name_last": "Lott",
        "person_address": "545 Middleton Street, Torboy, Texas, 40650",
        "person_risk_data": {
          "plan_type": "medicare advantage"
        }
      },
      {
        "person_id": "5fbb31ebbb37d9ca83c97752",
        "person_name_first": "Roseann",
        "person_name_last": "Cohen",
        "person_address": "159 Calder Place, Takilma, Michigan, 63578",
        "person_risk_data": {
          "plan_type": "medicare"
        }
      },
      {
        "person_id": "5fbb31eb346e254362d3895f",
        "person_name_first": "Marilyn",
        "person_name_last": "Chase",
        "person_address": "227 Flatlands Avenue, Wanamie, Idaho, 51206",
        "person_risk_data": {
          "plan_type": "medicare"
        }
      },
      {
        "person_id": "5fbb31ebfefc9a65a33a3abd",
        "person_name_first": "Burch",
        "person_name_last": "Gibson",
        "person_address": "631 Lefferts Place, Ladera, Alabama, 13517",
        "person_risk_data": {
          "plan_type": "medicare advantage"
        }
      },
      {
        "person_id": "5fbb31eb253d5f60dadf617f",
        "person_name_first": "Annmarie",
        "person_name_last": "Lawrence",
        "person_address": "330 Neptune Avenue, Gorham, Illinois, 61298",
        "person_risk_data": {
          "plan_type": "medicare advantage"
        }
      },
      {
        "person_id": "5fbb31eb9e251b34b689dd8a",
        "person_name_first": "Gates",
        "person_name_last": "Fields",
        "person_address": "744 Moore Place, Masthope, Oregon, 97397",
        "person_risk_data": {
          "plan_type": "medicare advantage"
        }
      },
      {
        "person_id": "5fbb31eb3ccc65aa04978ea2",
        "person_name_first": "Fernandez",
        "person_name_last": "Wolf",
        "person_address": "726 Terrace Place, Vallonia, Massachusetts, 71233",
        "person_risk_data": {
          "plan_type": "medicaid"
        }
      },
      {
        "person_id": "5fbb31ebcb386a6424247708",
        "person_name_first": "Sophie",
        "person_name_last": "Fowler",
        "person_address": "945 Judge Street, Rutherford, Kansas, 28835",
        "person_risk_data": {
          "plan_type": "medicare"
        }
      },
      {
        "person_id": "5fbb31eb2122b3e5bb28fe18",
        "person_name_first": "Maryanne",
        "person_name_last": "Hopper",
        "person_address": "757 Roebling Street, Hinsdale, New Hampshire, 46364",
        "person_risk_data": {
          "plan_type": "medicaid"
        }
      }
    ]
  },
  {
    "dataset_id": "5fbb31ebd47aea15e96e9051",
    "customer_id": "5fbabababaa1753e1928dda1",
    "dataset_title": "Dataset about members",
    "people": [
      {
        "person_id": "5fbb31ebaec680fb7715d95a",
        "person_name_first": "Victoria",
        "person_name_last": "Woods",
        "person_address": "985 Willoughby Avenue, Fidelis, Arizona, 16101",
        "person_risk_data": {
          "plan_type": "medicare advantage"
        }
      },
      {
        "person_id": "5fbb31eb1ad060a9362cf5a2",
        "person_name_first": "Tamara",
        "person_name_last": "Conley",
        "person_address": "898 Lexington Avenue, Villarreal, District Of Columbia, 69721",
        "person_risk_data": {
          "plan_type": "medicare advantage"
        }
      },
      {
        "person_id": "5fbb31eb80fe170e5d5231aa",
        "person_name_first": "Suzette",
        "person_name_last": "Murray",
        "person_address": "416 Pineapple Street, Lindisfarne, Guam, 38980",
        "person_risk_data": {
          "plan_type": "medicare advantage"
        }
      },
      {
        "person_id": "5fbb31eb86a256547cab81b9",
        "person_name_first": "Keith",
        "person_name_last": "Ochoa",
        "person_address": "365 Gunnison Court, Detroit, Vermont, 48755",
        "person_risk_data": {
          "plan_type": "medicaid"
        }
      },
      {
        "person_id": "5fbb31eb588ef592ca37d68e",
        "person_name_first": "Tamika",
        "person_name_last": "Garrison",
        "person_address": "972 Granite Street, Sexton, North Carolina, 96126",
        "person_risk_data": {
          "plan_type": "medicare"
        }
      }
    ]
  },
  {
    "dataset_id": "5fbb31eb09572105de6b00c5",
    "customer_id": "5fbabababaa1753e1928dda1",
    "dataset_title": "Dataset about members",
    "people": [
      {
        "person_id": "5fbb31eb4ec4c2703cba6bff",
        "person_name_first": "Tyler",
        "person_name_last": "Rojas",
        "person_address": "908 Herkimer Place, Lawrence, Ohio, 26112",
        "person_risk_data": {
          "plan_type": "medicare"
        }
      },
      {
        "person_id": "5fbb31ebc80672dc53919076",
        "person_name_first": "Mathis",
        "person_name_last": "Albert",
        "person_address": "523 Livingston Street, Cornucopia, Wyoming, 22353",
        "person_risk_data": {
          "plan_type": "medicare advantage"
        }
      },
      {
        "person_id": "5fbb31eb16acda817b4643b0",
        "person_name_first": "Bonita",
        "person_name_last": "Ellis",
        "person_address": "712 Glenwood Road, Caron, Louisiana, 92555",
        "person_risk_data": {
          "plan_type": "medicaid"
        }
      },
      {
        "person_id": "5fbb31ebc9b4d8b7b0dc8c70",
        "person_name_first": "Jerri",
        "person_name_last": "Velasquez",
        "person_address": "973 Eckford Street, Summerset, New Jersey, 51523",
        "person_risk_data": {
          "plan_type": "medicare advantage"
        }
      },
      {
        "person_id": "5fbb31eb1616398a608168dd",
        "person_name_first": "Sosa",
        "person_name_last": "Neal",
        "person_address": "697 Heath Place, Madaket, Tennessee, 81973",
        "person_risk_data": {
          "plan_type": "medicaid"
        }
      },
      {
        "person_id": "5fbb31ebcfa3ec51a7a87541",
        "person_name_first": "Spears",
        "person_name_last": "Sherman",
        "person_address": "810 Adelphi Street, Ada, Pennsylvania, 41671",
        "person_risk_data": {
          "plan_type": "medicare"
        }
      }
    ]
  },
  {
    "dataset_id": "5fbb31eb9fbd2920e30a2d86",
    "customer_id": "5fbababa93c0cf8b83f4d7cf",
    "dataset_title": "Dataset about members",
    "people": [
      {
        "person_id": "5fbb31eb84d34f693f14df69",
        "person_name_first": "Houston",
        "person_name_last": "Merrill",
        "person_address": "442 Herzl Street, Dunnavant, Maine, 38379",
        "person_risk_data": {
          "plan_type": "medicaid"
        }
      },
      {
        "person_id": "5fbb31eb3b3e8b0c5c6ca957",
        "person_name_first": "Gay",
        "person_name_last": "Buckley",
        "person_address": "269 Imlay Street, Worcester, Palau, 28297",
        "person_risk_data": {
          "plan_type": "medicaid"
        }
      },
      {
        "person_id": "5fbb31eb60570eae03ef2545",
        "person_name_first": "Juanita",
        "person_name_last": "Grimes",
        "person_address": "398 Everett Avenue, Gulf, South Dakota, 73797",
        "person_risk_data": {
          "plan_type": "medicare"
        }
      },
      {
        "person_id": "5fbb31ebcefe55a28824849b",
        "person_name_first": "Foster",
        "person_name_last": "Pollard",
        "person_address": "336 Irving Avenue, Terlingua, Northern Mariana Islands, 50246",
        "person_risk_data": {
          "plan_type": "medicaid"
        }
      },
      {
        "person_id": "5fbb31eb43c27eb41d3d54ab",
        "person_name_first": "Horn",
        "person_name_last": "Bridges",
        "person_address": "137 Bragg Court, Riverton, Kentucky, 55396",
        "person_risk_data": {
          "plan_type": "medicare"
        }
      },
      {
        "person_id": "5fbb31eba724bef268c9ac1a",
        "person_name_first": "Nicole",
        "person_name_last": "Finch",
        "person_address": "958 Madoc Avenue, Loomis, Utah, 95107",
        "person_risk_data": {
          "plan_type": "medicaid"
        }
      },
      {
        "person_id": "5fbb31eb7d54cbae8f0162a8",
        "person_name_first": "Rose",
        "person_name_last": "Beasley",
        "person_address": "532 Fanchon Place, Alfarata, Arkansas, 76239",
        "person_risk_data": {
          "plan_type": "medicare"
        }
      },
      {
        "person_id": "5fbb31ebe4bbff132cb9cc27",
        "person_name_first": "Austin",
        "person_name_last": "Mccullough",
        "person_address": "439 Hinckley Place, Tioga, Missouri, 30835",
        "person_risk_data": {
          "plan_type": "medicare advantage"
        }
      },
      {
        "person_id": "5fbb31eb46182029f7a243ba",
        "person_name_first": "Anne",
        "person_name_last": "Giles",
        "person_address": "803 Malta Street, Laurelton, South Carolina, 32119",
        "person_risk_data": {
          "plan_type": "medicaid"
        }
      },
      {
        "person_id": "5fbb31eb5b79c38d4ed25be8",
        "person_name_first": "Reilly",
        "person_name_last": "Banks",
        "person_address": "668 Wyona Street, Eureka, California, 42689",
        "person_risk_data": {
          "plan_type": "medicare"
        }
      }
    ]
  },
  {
    "dataset_id": "5fbb31ebbbe0f0bdd84dc5e1",
    "customer_id": "5fbababa717f10b546c261ba",
    "dataset_title": "Dataset about members",
    "people": [
      {
        "person_id": "5fbb31eb83f45de4c5466d15",
        "person_name_first": "Hewitt",
        "person_name_last": "Warner",
        "person_address": "382 Greenwood Avenue, Dola, Iowa, 32507",
        "person_risk_data": {
          "plan_type": "medicare"
        }
      },
      {
        "person_id": "5fbb31eb1b38a05281520830",
        "person_name_first": "Eileen",
        "person_name_last": "Mcconnell",
        "person_address": "817 Bay Avenue, Vowinckel, Wisconsin, 85800",
        "person_risk_data": {
          "plan_type": "medicare advantage"
        }
      },
      {
        "person_id": "5fbb31ebeb506da6e2c52f30",
        "person_name_first": "Mathews",
        "person_name_last": "Tyler",
        "person_address": "258 Seagate Avenue, Dana, Federated States Of Micronesia, 27314",
        "person_risk_data": {
          "plan_type": "medicaid"
        }
      },
      {
        "person_id": "5fbb31ebf74c58d459a2728e",
        "person_name_first": "Nicholson",
        "person_name_last": "Rivers",
        "person_address": "538 Battery Avenue, Heil, Virgin Islands, 54930",
        "person_risk_data": {
          "plan_type": "medicaid"
        }
      },
      {
        "person_id": "5fbb31eb06081ca020c2dbe1",
        "person_name_first": "Orr",
        "person_name_last": "Phelps",
        "person_address": "633 Herkimer Street, Blue, Nebraska, 63756",
        "person_risk_data": {
          "plan_type": "medicaid"
        }
      },
      {
        "person_id": "5fbb31eb683c11424cc6869c",
        "person_name_first": "Priscilla",
        "person_name_last": "Haynes",
        "person_address": "475 Townsend Street, Germanton, New York, 73597",
        "person_risk_data": {
          "plan_type": "medicare"
        }
      },
      {
        "person_id": "5fbb31ebf10792ca2f74d87a",
        "person_name_first": "Roberta",
        "person_name_last": "Case",
        "person_address": "328 Clifton Place, Edinburg, Colorado, 27960",
        "person_risk_data": {
          "plan_type": "medicare advantage"
        }
      },
      {
        "person_id": "5fbb31ebf9688214893acdab",
        "person_name_first": "Malinda",
        "person_name_last": "Prince",
        "person_address": "141 Cass Place, Deercroft, Marshall Islands, 64856",
        "person_risk_data": {
          "plan_type": "medicaid"
        }
      },
      {
        "person_id": "5fbb31ebeb880fa4738ffa03",
        "person_name_first": "Phillips",
        "person_name_last": "Skinner",
        "person_address": "377 Hawthorne Street, Baden, Hawaii, 48845",
        "person_risk_data": {
          "plan_type": "medicare"
        }
      }
    ]
  },
  {
    "dataset_id": "5fbb31eb5e1e9a3147f28b19",
    "customer_id": "5fbabababaa1753e1928dda1",
    "dataset_title": "Dataset about members",
    "people": [
      {
        "person_id": "5fbb31eb33b7c399978811f3",
        "person_name_first": "Melva",
        "person_name_last": "Waters",
        "person_address": "227 Seaview Court, Sperryville, Florida, 84329",
        "person_risk_data": {
          "plan_type": "medicare"
        }
      },
      {
        "person_id": "5fbb31eb8e29dc0e601805ee",
        "person_name_first": "Atkins",
        "person_name_last": "Randolph",
        "person_address": "822 Herbert Street, Bellamy, American Samoa, 38625",
        "person_risk_data": {
          "plan_type": "medicare advantage"
        }
      },
      {
        "person_id": "5fbb31eb2179f77b86421fb4",
        "person_name_first": "Powell",
        "person_name_last": "Hodge",
        "person_address": "508 Sedgwick Place, Bodega, Connecticut, 69609",
        "person_risk_data": {
          "plan_type": "medicare"
        }
      },
      {
        "person_id": "5fbb31eb30f4083f42658e91",
        "person_name_first": "Hatfield",
        "person_name_last": "Sweeney",
        "person_address": "439 Garfield Place, Tryon, Puerto Rico, 22181",
        "person_risk_data": {
          "plan_type": "medicare advantage"
        }
      },
      {
        "person_id": "5fbb31eb7340339759bfbc17",
        "person_name_first": "Le",
        "person_name_last": "Luna",
        "person_address": "768 Lacon Court, Croom, North Dakota, 29602",
        "person_risk_data": {
          "plan_type": "medicaid"
        }
      },
      {
        "person_id": "5fbb31ebbe3ba4ea84c488af",
        "person_name_first": "Boyd",
        "person_name_last": "Cortez",
        "person_address": "731 Coyle Street, Belfair, Nevada, 35751",
        "person_risk_data": {
          "plan_type": "medicare"
        }
      },
      {
        "person_id": "5fbb31eb9655cad6bd32a4be",
        "person_name_first": "Tammy",
        "person_name_last": "Bates",
        "person_address": "652 Eldert Lane, Dubois, Minnesota, 40500",
        "person_risk_data": {
          "plan_type": "medicare"
        }
      }
    ]
  },
  {
    "dataset_id": "5fbb31eb6edcb14d8d316b2c",
    "customer_id": "5fbababa527d1172a7fdc82d",
    "dataset_title": "Dataset about members",
    "people": [
      {
        "person_id": "5fbb31eb5930dd1c86255070",
        "person_name_first": "Strong",
        "person_name_last": "Whitfield",
        "person_address": "968 Hart Street, Beason, Montana, 60078",
        "person_risk_data": {
          "plan_type": "medicaid"
        }
      },
      {
        "person_id": "5fbb31eba0c3006d72dd7a00",
        "person_name_first": "Regina",
        "person_name_last": "Howell",
        "person_address": "829 Mermaid Avenue, Denio, Oklahoma, 57737",
        "person_risk_data": {
          "plan_type": "medicare"
        }
      },
      {
        "person_id": "5fbb31ebb592b50cc2354b79",
        "person_name_first": "Leon",
        "person_name_last": "Finley",
        "person_address": "351 Hart Place, Hayden, Rhode Island, 47982",
        "person_risk_data": {
          "plan_type": "medicare"
        }
      },
      {
        "person_id": "5fbb31ebd757584f9cabf126",
        "person_name_first": "Dona",
        "person_name_last": "Mayo",
        "person_address": "692 Conduit Boulevard, Deseret, Mississippi, 14596",
        "person_risk_data": {
          "plan_type": "medicare"
        }
      },
      {
        "person_id": "5fbb31eba51af0ff7f379e0a",
        "person_name_first": "Elvia",
        "person_name_last": "Sosa",
        "person_address": "883 Irwin Street, Norris, Alaska, 67031",
        "person_risk_data": {
          "plan_type": "medicare advantage"
        }
      },
      {
        "person_id": "5fbb31ebd7a1d438df96bd3d",
        "person_name_first": "Stuart",
        "person_name_last": "Chen",
        "person_address": "118 Ryerson Street, Orick, Indiana, 57933",
        "person_risk_data": {
          "plan_type": "medicare advantage"
        }
      },
      {
        "person_id": "5fbb31ebf7e7700e0f8861c6",
        "person_name_first": "Fields",
        "person_name_last": "Robles",
        "person_address": "250 Dekoven Court, Fingerville, West Virginia, 91939",
        "person_risk_data": {
          "plan_type": "medicare"
        }
      },
      {
        "person_id": "5fbb31eb9f4694be522eba98",
        "person_name_first": "Gracie",
        "person_name_last": "Goodwin",
        "person_address": "562 Bowery Street, Frizzleburg, Maryland, 42840",
        "person_risk_data": {
          "plan_type": "medicaid"
        }
      },
      {
        "person_id": "5fbb31eb631d1a80199355f7",
        "person_name_first": "Sparks",
        "person_name_last": "Wall",
        "person_address": "222 Amity Street, Harmon, Washington, 34144",
        "person_risk_data": {
          "plan_type": "medicare"
        }
      }
    ]
  },
  {
    "dataset_id": "5fbb31ebaaa7eb153fca71c6",
    "customer_id": "5fbababa717f10b546c261ba",
    "dataset_title": "Dataset about members",
    "people": [
      {
        "person_id": "5fbb31eb3cffb253d137e34c",
        "person_name_first": "Harris",
        "person_name_last": "Blanchard",
        "person_address": "364 Jackson Court, Crumpler, New Mexico, 28538",
        "person_risk_data": {
          "plan_type": "medicare advantage"
        }
      },
      {
        "person_id": "5fbb31ebc58ae460646c9b93",
        "person_name_first": "Dolly",
        "person_name_last": "Washington",
        "person_address": "146 Aberdeen Street, Deltaville, Virginia, 93323",
        "person_risk_data": {
          "plan_type": "medicaid"
        }
      },
      {
        "person_id": "5fbb31eb00174a8735734546",
        "person_name_first": "Carol",
        "person_name_last": "Christensen",
        "person_address": "513 School Lane, Wiscon, Delaware, 75287",
        "person_risk_data": {
          "plan_type": "medicaid"
        }
      },
      {
        "person_id": "5fbb31eb5ee5d9d2a2464774",
        "person_name_first": "Hoover",
        "person_name_last": "Malone",
        "person_address": "845 Cambridge Place, Stouchsburg, Texas, 96436",
        "person_risk_data": {
          "plan_type": "medicare"
        }
      },
      {
        "person_id": "5fbb31eba068f76f8c1effc7",
        "person_name_first": "Alana",
        "person_name_last": "Clay",
        "person_address": "417 Strauss Street, Sharon, Michigan, 61374",
        "person_risk_data": {
          "plan_type": "medicaid"
        }
      },
      {
        "person_id": "5fbb31eb7a7ddd91fbe9e7b4",
        "person_name_first": "Yvonne",
        "person_name_last": "Tillman",
        "person_address": "816 Newport Street, Barstow, Idaho, 62111",
        "person_risk_data": {
          "plan_type": "medicare advantage"
        }
      },
      {
        "person_id": "5fbb31eb4e694f8b0540d110",
        "person_name_first": "Sharron",
        "person_name_last": "Hunt",
        "person_address": "385 Tudor Terrace, Nanafalia, Alabama, 50235",
        "person_risk_data": {
          "plan_type": "medicare"
        }
      }
    ]
  },
  {
    "dataset_id": "5fbb31eb137644a1085c20be",
    "customer_id": "5fbababa527d1172a7fdc82d",
    "dataset_title": "Dataset about members",
    "people": [
      {
        "person_id": "5fbb31ebeb91e9d5ce0bae65",
        "person_name_first": "Betsy",
        "person_name_last": "Horn",
        "person_address": "110 Monaco Place, Robinson, Illinois, 40040",
        "person_risk_data": {
          "plan_type": "medicare advantage"
        }
      },
      {
        "person_id": "5fbb31eb8e97f5186f4726b5",
        "person_name_first": "Clarke",
        "person_name_last": "Newman",
        "person_address": "351 Kingsland Avenue, Ola, Oregon, 40144",
        "person_risk_data": {
          "plan_type": "medicare"
        }
      },
      {
        "person_id": "5fbb31eb49366e9ea7afbe37",
        "person_name_first": "Barbara",
        "person_name_last": "Delaney",
        "person_address": "715 Scholes Street, Iola, Massachusetts, 28393",
        "person_risk_data": {
          "plan_type": "medicare advantage"
        }
      },
      {
        "person_id": "5fbb31eb5ff9411e2857705a",
        "person_name_first": "Rosie",
        "person_name_last": "Atkinson",
        "person_address": "849 Kingston Avenue, Bergoo, Kansas, 36892",
        "person_risk_data": {
          "plan_type": "medicare"
        }
      },
      {
        "person_id": "5fbb31ebc3b6f9381e1b2a35",
        "person_name_first": "Estelle",
        "person_name_last": "Benson",
        "person_address": "957 Wilson Avenue, Soudan, New Hampshire, 28348",
        "person_risk_data": {
          "plan_type": "medicare advantage"
        }
      }
    ]
  },
  {
    "dataset_id": "5fbb31eb7cb5f152ae5035f7",
    "customer_id": "5fbababa93c0cf8b83f4d7cf",
    "dataset_title": "Dataset about members",
    "people": [
      {
        "person_id": "5fbb31eb04b1b68bafe33b7d",
        "person_name_first": "Charlene",
        "person_name_last": "Colon",
        "person_address": "351 Argyle Road, Indio, Arizona, 76398",
        "person_risk_data": {
          "plan_type": "medicare advantage"
        }
      },
      {
        "person_id": "5fbb31eb345a41b6de1a5638",
        "person_name_first": "Daugherty",
        "person_name_last": "Livingston",
        "person_address": "776 Hendrix Street, Brewster, District Of Columbia, 44057",
        "person_risk_data": {
          "plan_type": "medicare advantage"
        }
      },
      {
        "person_id": "5fbb31eb968784a03291005c",
        "person_name_first": "Branch",
        "person_name_last": "Park",
        "person_address": "306 Chester Avenue, Mappsville, Guam, 34661",
        "person_risk_data": {
          "plan_type": "medicaid"
        }
      },
      {
        "person_id": "5fbb31ebfdb645c61d22e221",
        "person_name_first": "Nola",
        "person_name_last": "Dennis",
        "person_address": "108 Taaffe Place, Oberlin, Vermont, 95137",
        "person_risk_data": {
          "plan_type": "medicaid"
        }
      },
      {
        "person_id": "5fbb31ebc4a1d2d5edca7b7f",
        "person_name_first": "Michael",
        "person_name_last": "Kim",
        "person_address": "939 Wolf Place, Elizaville, North Carolina, 72012",
        "person_risk_data": {
          "plan_type": "medicare"
        }
      },
      {
        "person_id": "5fbb31ebae804996184bc9eb",
        "person_name_first": "Patrick",
        "person_name_last": "Cox",
        "person_address": "551 Division Avenue, Echo, Ohio, 65742",
        "person_risk_data": {
          "plan_type": "medicare"
        }
      },
      {
        "person_id": "5fbb31ebcecb153324189730",
        "person_name_first": "Randolph",
        "person_name_last": "Warren",
        "person_address": "847 Amboy Street, Winchester, Wyoming, 40357",
        "person_risk_data": {
          "plan_type": "medicaid"
        }
      },
      {
        "person_id": "5fbb31eb3e93b2370371e226",
        "person_name_first": "Neva",
        "person_name_last": "Nielsen",
        "person_address": "243 Bergen Street, Chilton, Louisiana, 59356",
        "person_risk_data": {
          "plan_type": "medicaid"
        }
      },
      {
        "person_id": "5fbb31eb12ea8e1167a2f0dd",
        "person_name_first": "Christi",
        "person_name_last": "Turner",
        "person_address": "282 Chestnut Avenue, Inkerman, New Jersey, 38086",
        "person_risk_data": {
          "plan_type": "medicare advantage"
        }
      },
      {
        "person_id": "5fbb31eb8b786e7af40ce527",
        "person_name_first": "Elnora",
        "person_name_last": "Rich",
        "person_address": "958 Roosevelt Court, Moscow, Tennessee, 28561",
        "person_risk_data": {
          "plan_type": "medicaid"
        }
      }
    ]
  },
  {
    "dataset_id": "5fbb31ebb32649eebc9d24f4",
    "customer_id": "5fbabababaa1753e1928dda1",
    "dataset_title": "Dataset about members",
    "people": [
      {
        "person_id": "5fbb31eb71c5cfe4a8cacde8",
        "person_name_first": "Ophelia",
        "person_name_last": "Lowe",
        "person_address": "155 Pitkin Avenue, Tibbie, Pennsylvania, 90647",
        "person_risk_data": {
          "plan_type": "medicare advantage"
        }
      },
      {
        "person_id": "5fbb31eb5cc99ed427cc039f",
        "person_name_first": "Shepard",
        "person_name_last": "Dixon",
        "person_address": "207 Fane Court, Fairmount, Maine, 40886",
        "person_risk_data": {
          "plan_type": "medicare"
        }
      },
      {
        "person_id": "5fbb31eb6ca196464e2c6a26",
        "person_name_first": "Wheeler",
        "person_name_last": "Spencer",
        "person_address": "961 Newkirk Placez, Collins, Palau, 40179",
        "person_risk_data": {
          "plan_type": "medicare advantage"
        }
      },
      {
        "person_id": "5fbb31eb9b019deba27a999a",
        "person_name_first": "Sabrina",
        "person_name_last": "Meadows",
        "person_address": "338 Berry Street, Callaghan, South Dakota, 31575",
        "person_risk_data": {
          "plan_type": "medicare advantage"
        }
      },
      {
        "person_id": "5fbb31eb765f5c1d29b32ba3",
        "person_name_first": "Sargent",
        "person_name_last": "Wooten",
        "person_address": "961 Fuller Place, Topanga, Northern Mariana Islands, 91269",
        "person_risk_data": {
          "plan_type": "medicare advantage"
        }
      },
      {
        "person_id": "5fbb31eb334889f504b54973",
        "person_name_first": "Nelson",
        "person_name_last": "Cannon",
        "person_address": "676 Lincoln Avenue, Retsof, Kentucky, 91397",
        "person_risk_data": {
          "plan_type": "medicare advantage"
        }
      },
      {
        "person_id": "5fbb31eb8b590eab7483aa8f",
        "person_name_first": "Banks",
        "person_name_last": "Morgan",
        "person_address": "167 Willow Place, Leland, Utah, 76409",
        "person_risk_data": {
          "plan_type": "medicare"
        }
      }
    ]
  }
]